test
smtproutes
