Metadata-Version: 1.0
Name: smtproutes
Version: 1.2.7
Summary: A simple, Sinatra inspired, SMTP routing server.
Home-page: https://github.com/bcoe/smtproutes
Author: Benjamin Coe
Author-email: bencoe@gmail.com
License: UNKNOWN
Platform: UNKNOWN
